gauss_lm_mle/__init__.py
gauss_lm_mle/fitters.py
gauss_lm_mle/liblm_mle_de.py
gauss_lm_mle/lm_mle_de.cpython-310-darwin.so
gauss_lm_mle/utils.py
gauss_lm_mle-0.1.2.dist-info/LICENSE
gauss_lm_mle-0.1.2.dist-info/METADATA
gauss_lm_mle-0.1.2.dist-info/WHEEL
gauss_lm_mle-0.1.2.dist-info/top_level.txt
gauss_lm_mle-0.1.2.dist-info/RECORD
